{
  "disease": "cardiac",
  "n_folds": 5,
  "folds": [
    {
      "fold": 1,
      "n_train_patients": 80,
      "n_test_patients": 20,
      "n_train": 111600,
      "n_test": 27900,
      "roc_auc": 0.9266,
      "pr_auc": 0.8183,
      "f1": 0.7687,
      "best_iter": 10
    },
    {
      "fold": 2,
      "n_train_patients": 80,
      "n_test_patients": 20,
      "n_train": 111600,
      "n_test": 27900,
      "roc_auc": 0.9244,
      "pr_auc": 0.8152,
      "f1": 0.8416,
      "best_iter": 112
    },
    {
      "fold": 3,
      "n_train_patients": 80,
      "n_test_patients": 20,
      "n_train": 111600,
      "n_test": 27900,
      "roc_auc": 0.9072,
      "pr_auc": 0.8421,
      "f1": 0.8299,
      "best_iter": 230
    },
    {
      "fold": 4,
      "n_train_patients": 80,
      "n_test_patients": 20,
      "n_train": 111600,
      "n_test": 27900,
      "roc_auc": 0.8818,
      "pr_auc": 0.7443,
      "f1": 0.7861,
      "best_iter": 24
    },
    {
      "fold": 5,
      "n_train_patients": 80,
      "n_test_patients": 20,
      "n_train": 111600,
      "n_test": 27900,
      "roc_auc": 0.8861,
      "pr_auc": 0.8195,
      "f1": 0.8459,
      "best_iter": 246
    }
  ],
  "mean_roc_auc": 0.9052,
  "std_roc_auc": 0.0187,
  "mean_pr_auc": 0.8079,
  "std_pr_auc": 0.0332,
  "mean_f1": 0.8144,
  "std_f1": 0.0312
}